__init__.py
api_client.py
api_response.py
configuration.py
exceptions.py
py.typed
rest.py
template_python_client-0.1.1.dist-info/LICENSE
template_python_client-0.1.1.dist-info/METADATA
template_python_client-0.1.1.dist-info/WHEEL
template_python_client-0.1.1.dist-info/RECORD
