Metadata-Version: 2.1
Name: template_python_client
Version: 0.1.1
Summary: Template web service
License: MIT
Keywords: OpenAPI,OpenAPI-Generator,Template web service
Author: HIRO-MicroDataCenters
Author-email: all-hiro@hiro-microdatacenters.nl
Requires-Python: >=3.7,<4.0
Classifier: License :: OSI Approved :: MIT License
Classifier: Programming Language :: Python :: 3
Classifier: Programming Language :: Python :: 3.7
Classifier: Programming Language :: Python :: 3.8
Classifier: Programming Language :: Python :: 3.9
Classifier: Programming Language :: Python :: 3.10
Classifier: Programming Language :: Python :: 3.11
Classifier: Programming Language :: Python :: 3.12
Requires-Dist: pydantic (>=2)
Requires-Dist: python-dateutil (>=2.8.2)
Requires-Dist: typing-extensions (>=4.7.1)
Requires-Dist: urllib3 (>=1.25.3)
